wirtual/plugins/openai/__init__.py
wirtual/plugins/openai/_oai_api.py
wirtual/plugins/openai/embeddings.py
wirtual/plugins/openai/llm.py
wirtual/plugins/openai/log.py
wirtual/plugins/openai/models.py
wirtual/plugins/openai/py.typed
wirtual/plugins/openai/stt.py
wirtual/plugins/openai/tts.py
wirtual/plugins/openai/utils.py
wirtual/plugins/openai/version.py
wirtual/plugins/openai/beta/__init__.py
wirtual/plugins/openai/beta/assistant_llm.py
wirtual/plugins/openai/realtime/__init__.py
wirtual/plugins/openai/realtime/api_proto.py
wirtual/plugins/openai/realtime/log.py
wirtual/plugins/openai/realtime/realtime_model.py
wirtual/plugins/openai/realtime/remote_items.py
wirtual_plugins_openai-0.0.2.dist-info/METADATA
wirtual_plugins_openai-0.0.2.dist-info/WHEEL
wirtual_plugins_openai-0.0.2.dist-info/top_level.txt
wirtual_plugins_openai-0.0.2.dist-info/RECORD
